mcp_lumerpy/__init__.py
mcp_lumerpy/mcp_server.py
mcp_lumerpy-0.2.3.dist-info/entry_points.txt
mcp_lumerpy-0.2.3.dist-info/METADATA
mcp_lumerpy-0.2.3.dist-info/WHEEL
mcp_lumerpy-0.2.3.dist-info/RECORD
