Metadata-Version: 2.3
Name: mcp-lumerpy
Version: 0.2.3
Summary: Official MCP wrapper for the lumerpy simulation library
License: MIT
Author: OscarxChen
Author-email: oscarxchen@outlook.com
Requires-Python: >=3.8
Classifier: License :: OSI Approved :: MIT License
Classifier: Programming Language :: Python :: 3
Classifier: Programming Language :: Python :: 3.8
Classifier: Programming Language :: Python :: 3.9
Classifier: Programming Language :: Python :: 3.10
Classifier: Programming Language :: Python :: 3.11
Classifier: Programming Language :: Python :: 3.12
Classifier: Programming Language :: Python :: 3.13
Requires-Dist: lumerpy (>=1.3.0)
Requires-Dist: mcp (>=1.9,<2.0)
Project-URL: Homepage, https://github.com/OscarXChen/mcp-lumerpy
Project-URL: Repository, https://github.com/OscarXChen/mcp-lumerpy
